pyIsEmail/__about__.py
pyIsEmail/__init__.py
pyIsEmail/email_validator.py
pyIsEmail/reference.py
pyIsEmail/utils.py
pyIsEmail/diagnosis/__init__.py
pyIsEmail/diagnosis/base_diagnosis.py
pyIsEmail/diagnosis/cfws_diagnosis.py
pyIsEmail/diagnosis/deprecated_diagnosis.py
pyIsEmail/diagnosis/dns_diagnosis.py
pyIsEmail/diagnosis/gtld_diagnosis.py
pyIsEmail/diagnosis/invalid_diagnosis.py
pyIsEmail/diagnosis/rfc5321_diagnosis.py
pyIsEmail/diagnosis/rfc5322_diagnosis.py
pyIsEmail/diagnosis/valid_diagnosis.py
pyIsEmail/validators/__init__.py
pyIsEmail/validators/dns_validator.py
pyIsEmail/validators/gtld_validator.py
pyIsEmail/validators/parser_validator.py
pyisemail-2.0.0.dist-info/METADATA
pyisemail-2.0.0.dist-info/WHEEL
pyisemail-2.0.0.dist-info/licenses/LICENSE
pyisemail-2.0.0.dist-info/RECORD
