Metadata-Version: 2.1
Name: pyIsEmail
Version: 2.0.0
Summary: Simple, robust email validation
Project-URL: Homepage, https://github.com/michaelherold/pyIsEmail
Project-URL: Source, https://github.com/michaelherold/pyIsEmail
Project-URL: Tracker, https://github.com/michaelherold/pyIsEmail/issues
Author-email: Michael Herold <opensource@michaeljherold.com>
License-File: LICENSE
Keywords: email,validation
Classifier: Development Status :: 5 - Production/Stable
Classifier: Intended Audience :: Developers
Classifier: License :: OSI Approved :: MIT License
Classifier: Operating System :: OS Independent
Classifier: Programming Language :: Python :: 3
Classifier: Programming Language :: Python :: 3 :: Only
Classifier: Programming Language :: Python :: 3.7
Classifier: Programming Language :: Python :: 3.8
Classifier: Programming Language :: Python :: 3.9
Classifier: Programming Language :: Python :: 3.10
Classifier: Programming Language :: Python :: Implementation :: PyPy
Classifier: Topic :: Communications :: Email
Classifier: Topic :: Software Development :: Libraries :: Python Modules
Requires-Python: >=3.7
Requires-Dist: dnspython>=2.0.0
